animegifs/__init__.py
animegifs/animegifs.py
animegifs/distutils/__init__.py
animegifs/distutils/errors.py
animegifs-1.2.2.dist-info/licenses/LICENSE
animegifs-1.2.2.dist-info/METADATA
animegifs-1.2.2.dist-info/WHEEL
animegifs-1.2.2.dist-info/top_level.txt
animegifs-1.2.2.dist-info/RECORD
