Metadata-Version: 2.4
Name: animegifs
Version: 1.2.2
Summary: Get random anime gifs by category.
Home-page: https://github.com/MarcoSa-2000/animegifs
Author: Marco-Sa2000
Author-email: grest0grest@gmail.com
License: MIT
Keywords: anime,gif,python,anime-gifs,discord
Classifier: Programming Language :: Python :: 3.8
Classifier: Programming Language :: Python :: 3.9
Classifier: Programming Language :: Python :: 3.10
Classifier: Programming Language :: Python :: 3.11
Classifier: Programming Language :: Python :: 3.12
Classifier: Programming Language :: Python :: 3.13
Classifier: License :: OSI Approved :: MIT License
Classifier: Operating System :: Microsoft :: Windows
Requires-Python: >=3.8
License-File: LICENSE
Requires-Dist: requests>=2.32.5
Requires-Dist: mal-api==0.5.3
Dynamic: author
Dynamic: author-email
Dynamic: classifier
Dynamic: description
Dynamic: description-content-type
Dynamic: home-page
Dynamic: keywords
Dynamic: license
Dynamic: license-file
Dynamic: requires-dist
Dynamic: requires-python
Dynamic: summary
